llama_index/postprocessor/presidio/__init__.py
llama_index/postprocessor/presidio/base.py
llama_index_postprocessor_presidio-0.5.1.dist-info/METADATA
llama_index_postprocessor_presidio-0.5.1.dist-info/WHEEL
llama_index_postprocessor_presidio-0.5.1.dist-info/licenses/LICENSE
llama_index_postprocessor_presidio-0.5.1.dist-info/RECORD
