Metadata-Version: 2.4
Name: llama-index-postprocessor-presidio
Version: 0.5.1
Summary: llama-index postprocessor presidio integration
Author-email: Your Name <you@example.com>
Maintainer: roeybc
License-Expression: MIT
License-File: LICENSE
Requires-Python: <4.0,>=3.9
Requires-Dist: llama-index-core<0.15,>=0.13.0
Requires-Dist: presidio-analyzer<3,>=2.2.353
Requires-Dist: presidio-anonymizer<3,>=2.2.353
